Master/12_patterndet_static_dynamic_ov_nonov_mealy_moore/bbcbc.v
module fsm(in,rst,clk,out);
input in, rst, clk;
output reg out;
integer count;
reg [2:0]ps, ns;

parameter reset=0, b=1,bb=2,bbc=3,bbcb=4, bbcbc=5;

always @(posedge clk or posedge rst)
	begin
		if (rst)
			ps<=reset;
		else 
			ps<=ns;

	end
//0=b,1=c
initial begin
count=0;
end
always @(ps or in)
	begin
		case (ps)
			reset: begin
				ns=in?reset:b;
				out=0;
			end
			b: begin
				ns=in?reset:bb;
				out=0;
			end

			bb: begin
				ns=in?bbc:bb;
				out=0;
			end
			bbc: begin
				ns=in?reset:bbcb;
				out=0;
			end
			bbcb: begin
				ns=in?bbcbc:bb;
				out=0;
			end
			bbcbc: begin
				ns=in?reset:b;
				out=1;
				count=count+1;
			end
		endcase
	end

initial begin

	$monitor("count=%0d",count);
end
endmodule

Master/12_patterndet_static_dynamic_ov_nonov_mealy_moore/bbcbc_mealy_tb.v
`include"bbcbc_mealy.v"
module tb;
reg in, rst, clk;
wire out;

fsm dut(in,rst,clk,out);

always begin
#5 clk=0;
#5 clk=1;
end

initial begin
rst=1'b1;
#15 rst=1'b0;

  repeat (600) begin
  @(posedge clk); //check why only this delay is working and why not others
 in=$random;
end
#50;
$finish;
end
 initial begin
    $dumpfile("1.vcd");
    $dumpvars();
  end
endmodule

Master/12_patterndet_static_dynamic_ov_nonov_mealy_moore/1.vcd
$date
	Wed Oct 20 15:48:32 2021
$end
$version
	ModelSim Version 2021.1
$end
$timescale
	1ps
$end

$scope module tb $end
$var reg 1 ! in $end
$var reg 1 " rst $end
$var reg 1 # clk $end
$var wire 1 $ out $end

$scope module dut $end
$var parameter 32 % reset $end
$var parameter 32 & b $end
$var parameter 32 ' bb $end
$var parameter 32 ( bbc $end
$var parameter 32 ) bbcb $end
$var wire 1 * in $end
$var wire 1 + rst $end
$var wire 1 , clk $end
$var reg 1 - out $end
$var integer 32 . count $end
$var reg 3 / ps [2:0] $end
$var reg 3 0 ns [2:0] $end
$upscope $end
$upscope $end
$enddefinitions $end
#0
$dumpvars
x!
1"
x#
0-
b0 /
b0x 0
b0 %
b1 &
b10 '
b11 (
b100 )
b0 .
0$
x,
1+
x*
$end
#5
0#
0,
#10
1#
1,
#15
0"
0#
0+
0,
#20
1#
1,
0!
0*
b1 0
b0x /
#25
0#
0,
#30
1#
1,
1!
1*
b1 /
b0 0
#35
0#
0,
#40
1#
1,
b0 /
#45
0#
0,
#50
1#
1,
#55
0#
0,
#60
1#
1,
#65
0#
0,
#70
1#
1,
#75
0#
0,
#80
1#
1,
#85
0#
0,
#90
1#
1,
0!
0*
b1 0
#95
0#
0,
#100
1#
1,
1!
1*
b0 0
b1 /
#105
0#
0,
#110
1#
1,
b0 /
#115
0#
0,
#120
1#
1,
0!
0*
b1 0
#125
0#
0,
#130
1#
1,
1!
1*
b0 0
b1 /
#135
0#
0,
#140
1#
1,
b0 /
#145
0#
0,
#150
1#
1,
0!
0*
b1 0
#155
0#
0,
#160
1#
1,
1!
1*
b0 0
b1 /
#165
0#
0,
#170
1#
1,
0!
0*
b10 0
b0 /
b1 0
#175
0#
0,
#180
1#
1,
1!
1*
b0 0
b1 /
#185
0#
0,
#190
1#
1,
0!
0*
b10 0
b0 /
b1 0
#195
0#
0,
#200
1#
1,
1!
1*
b0 0
b1 /
#205
0#
0,
#210
1#
1,
b0 /
#215
0#
0,
#220
1#
1,
0!
0*
b1 0
#225
0#
0,
#230
1#
1,
1!
1*
b0 0
b1 /
#235
0#
0,
#240
1#
1,
0!
0*
b10 0
b0 /
b1 0
#245
0#
0,
#250
1#
1,
b1 /
b10 0
#255
0#
0,
#260
1#
1,
b10 /
#265
0#
0,
#270
1#
1,
1!
1*
b11 0
#275
0#
0,
#280
1#
1,
0!
0*
b10 0
b11 /
b100 0
#285
0#
0,
#290
1#
1,
1!
1*
b0 0
b100 /
1-
b1 .
1$
#295
0#
0,
#300
1#
1,
b0 /
0-
0$
#305
0#
0,
#310
1#
1,
#315
0#
0,
#320
1#
1,
#325
0#
0,
#330
1#
1,
0!
0*
b1 0
#335
0#
0,
#340
1#
1,
b1 /
b10 0
#345
0#
0,
#350
1#
1,
b10 /
#355
0#
0,
#360
1#
1,
#365
0#
0,
#370
1#
1,
1!
1*
b11 0
#375
0#
0,
#380
1#
1,
0!
0*
b10 0
b11 /
b100 0
#385
0#
0,
#390
1#
1,
1!
1*
b0 0
b100 /
1-
b10 .
1$
#395
0#
0,
#400
1#
1,
b0 /
0-
0$
#405
0#
0,
#410
1#
1,
#415
0#
0,
#420
1#
1,
#425
0#
0,
#430
1#
1,
#435
0#
0,
#440
1#
1,
0!
0*
b1 0
#445
0#
0,
#450
1#
1,
b1 /
b10 0
#455
0#
0,
#460
1#
1,
1!
1*
b0 0
b10 /
b11 0
#465
0#
0,
#470
1#
1,
b11 /
b0 0
#475
0#
0,
#480
1#
1,
b0 /
#485
0#
0,
#490
1#
1,
0!
0*
b1 0
#495
0#
0,
#500
1#
1,
b1 /
b10 0
#505
0#
0,
#510
1#
1,
b10 /
#515
0#
0,
#520
1#
1,
#525
0#
0,
#530
1#
1,
#535
0#
0,
#540
1#
1,
1!
1*
b11 0
#545
0#
0,
#550
1#
1,
0!
0*
b10 0
b11 /
b100 0
#555
0#
0,
#560
1#
1,
b100 /
b10 0
#565
0#
0,
#570
1#
1,
1!
1*
b0 0
1-
b11 .
1$
b10 /
b11 0
0-
0$
#575
0#
0,
#580
1#
1,
b11 /
b0 0
#585
0#
0,
#590
1#
1,
0!
0*
b100 0
b0 /
b1 0
#595
0#
0,
#600
1#
1,
b1 /
b10 0
#605
0#
0,
#610
1#
1,
b10 /
#615
0#
0,
#620
1#
1,
#625
0#
0,
#630
1#
1,
#635
0#
0,
#640
1#
1,
1!
1*
b11 0
#645
0#
0,
#650
1#
1,
b11 /
b0 0
#655
0#
0,
#660
1#
1,
b0 /
#665
0#
0,
#670
1#
1,
#675
0#
0,
#680
1#
1,
#685
0#
0,
#690
1#
1,
0!
0*
b1 0
#695
0#
0,
#700
1#
1,
b1 /
b10 0
#705
0#
0,
#710
1#
1,
1!
1*
b0 0
b10 /
b11 0
#715
0#
0,
#720
1#
1,
b11 /
b0 0
#725
0#
0,
#730
1#
1,
b0 /
#735
0#
0,
#740
1#
1,
0!
0*
b1 0
#745
0#
0,
#750
1#
1,
b1 /
b10 0
#755
0#
0,
#760
1#
1,
1!
1*
b0 0
b10 /
b11 0
#765
0#
0,
#770
1#
1,
b11 /
b0 0
#775
0#
0,
#780
1#
1,
0!
0*
b100 0
b0 /
b1 0
#785
0#
0,
#790
1#
1,
1!
1*
b0 0
b1 /
#795
0#
0,
#800
1#
1,
b0 /
#805
0#
0,
#810
1#
1,
0!
0*
b1 0
#815
0#
0,
#820
1#
1,
1!
1*
b0 0
b1 /
#825
0#
0,
#830
1#
1,
b0 /
#835
0#
0,
#840
1#
1,
#845
0#
0,
#850
1#
1,
0!
0*
b1 0
#855
0#
0,
#860
1#
1,
1!
1*
b0 0
b1 /
#865
0#
0,
#870
1#
1,
b0 /
#875
0#
0,
#880
1#
1,
0!
0*
b1 0
#885
0#
0,
#890
1#
1,
b1 /
b10 0
#895
0#
0,
#900
1#
1,
b10 /
#905
0#
0,
#910
1#
1,
#915
0#
0,
#920
1#
1,
1!
1*
b11 0
#925
0#
0,
#930
1#
1,
b11 /
b0 0
#935
0#
0,
#940
1#
1,
0!
0*
b100 0
b0 /
b1 0
#945
0#
0,
#950
1#
1,
b1 /
b10 0
#955
0#
0,
#960
1#
1,
1!
1*
b0 0
b10 /
b11 0
#965
0#
0,
#970
1#
1,
b11 /
b0 0
#975
0#
0,
#980
1#
1,
b0 /
#985
0#
0,
#990
1#
1,
#995
0#
0,
#1000
1#
1,
#1005
0#
0,
#1010
1#
1,
0!
0*
b1 0
#1015
0#
0,
#1020
1#
1,
1!
1*
b0 0
b1 /
#1025
0#
0,
#1030
1#
1,
b0 /
#1035
0#
0,
#1040
1#
1,
#1045
0#
0,
#1050
1#
1,
0!
0*
b1 0
#1055
0#
0,
#1060
1#
1,
b1 /
b10 0
#1065
0#
0,
#1070
1#
1,
b10 /
#1075
0#
0,
#1080
1#
1,
#1085
0#
0,
#1090
1#
1,
#1095
0#
0,
#1100
1#
1,
#1105
0#
0,
#1110
1#
1,
#1115
0#
0,
#1120
1#
1,
1!
1*
b11 0
#1125
0#
0,
#1130
1#
1,
b11 /
b0 0
#1135
0#
0,
#1140
1#
1,
b0 /
#1145
0#
0,
#1150
1#
1,
#1155
0#
0,
#1160
1#
1,
#1165
0#
0,
#1170
1#
1,
0!
0*
b1 0
#1175
0#
0,
#1180
1#
1,
1!
1*
b0 0
b1 /
#1185
0#
0,
#1190
1#
1,
b0 /
#1195
0#
0,
#1200
1#
1,
0!
0*
b1 0
#1205
0#
0,
#1210
1#
1,
b1 /
b10 0
#1215
0#
0,
#1220
1#
1,
1!
1*
b0 0
b10 /
b11 0
#1225
0#
0,
#1230
1#
1,
b11 /
b0 0
#1235
0#
0,
#1240
1#
1,
0!
0*
b100 0
b0 /
b1 0
#1245
0#
0,
#1250
1#
1,
1!
1*
b0 0
b1 /
#1255
0#
0,
#1260
1#
1,
b0 /
#1265
0#
0,
#1270
1#
1,
#1275
0#
0,
#1280
1#
1,
#1285
0#
0,
#1290
1#
1,
0!
0*
b1 0
#1295
0#
0,
#1300
1#
1,
b1 /
b10 0
#1305
0#
0,
#1310
1#
1,
b10 /
#1315
0#
0,
#1320
1#
1,
1!
1*
b11 0
#1325
0#
0,
#1330
1#
1,
0!
0*
b10 0
b11 /
b100 0
#1335
0#
0,
#1340
1#
1,
b100 /
b10 0
#1345
0#
0,
#1350
1#
1,
b10 /
#1355
0#
0,
#1360
1#
1,
1!
1*
b11 0
#1365
0#
0,
#1370
1#
1,
b11 /
b0 0
#1375
0#
0,
#1380
1#
1,
0!
0*
b100 0
b0 /
b1 0
#1385
0#
0,
#1390
1#
1,
b1 /
b10 0
#1395
0#
0,
#1400
1#
1,
1!
1*
b0 0
b10 /
b11 0
#1405
0#
0,
#1410
1#
1,
0!
0*
b10 0
b11 /
b100 0
#1415
0#
0,
#1420
1#
1,
b100 /
b10 0
#1425
0#
0,
#1430
1#
1,
b10 /
#1435
0#
0,
#1440
1#
1,
1!
1*
b11 0
#1445
0#
0,
#1450
1#
1,
0!
0*
b10 0
b11 /
b100 0
#1455
0#
0,
#1460
1#
1,
b100 /
b10 0
#1465
0#
0,
#1470
1#
1,
1!
1*
b0 0
1-
b100 .
1$
b10 /
b11 0
0-
0$
#1475
0#
0,
#1480
1#
1,
0!
0*
b10 0
b11 /
b100 0
#1485
0#
0,
#1490
1#
1,
1!
1*
b0 0
b100 /
1-
b101 .
1$
#1495
0#
0,
#1500
1#
1,
b0 /
0-
0$
#1505
0#
0,
#1510
1#
1,
#1515
0#
0,
#1520
1#
1,
#1525
0#
0,
#1530
1#
1,
#1535
0#
0,
#1540
1#
1,
0!
0*
b1 0
#1545
0#
0,
#1550
1#
1,
b1 /
b10 0
#1555
0#
0,
#1560
1#
1,
b10 /
#1565
0#
0,
#1570
1#
1,
1!
1*
b11 0
#1575
0#
0,
#1580
1#
1,
0!
0*
b10 0
b11 /
b100 0
#1585
0#
0,
#1590
1#
1,
b100 /
b10 0
#1595
0#
0,
#1600
1#
1,
1!
1*
b0 0
1-
b110 .
1$
b10 /
b11 0
0-
0$
#1605
0#
0,
#1610
1#
1,
b11 /
b0 0
#1615
0#
0,
#1620
1#
1,
0!
0*
b100 0
b0 /
b1 0
#1625
0#
0,
#1630
1#
1,
b1 /
b10 0
#1635
0#
0,
#1640
1#
1,
b10 /
#1645
0#
0,
#1650
1#
1,
1!
1*
b11 0
#1655
0#
0,
#1660
1#
1,
b11 /
b0 0
#1665
0#
0,
#1670
1#
1,
0!
0*
b100 0
b0 /
b1 0
#1675
0#
0,
#1680
1#
1,
b1 /
b10 0
#1685
0#
0,
#1690
1#
1,
b10 /
#1695
0#
0,
#1700
1#
1,
1!
1*
b11 0
#1705
0#
0,
#1710
1#
1,
b11 /
b0 0
#1715
0#
0,
#1720
1#
1,
0!
0*
b100 0
b0 /
b1 0
#1725
0#
0,
#1730
1#
1,
b1 /
b10 0
#1735
0#
0,
#1740
1#
1,
b10 /
#1745
0#
0,
#1750
1#
1,
1!
1*
b11 0
#1755
0#
0,
#1760
1#
1,
0!
0*
b10 0
b11 /
b100 0
#1765
0#
0,
#1770
1#
1,
b100 /
b10 0
#1775
0#
0,
#1780
1#
1,
1!
1*
b0 0
1-
b111 .
1$
b10 /
b11 0
0-
0$
#1785
0#
0,
#1790
1#
1,
0!
0*
b10 0
b11 /
b100 0
#1795
0#
0,
#1800
1#
1,
b100 /
b10 0
#1805
0#
0,
#1810
1#
1,
b10 /
#1815
0#
0,
#1820
1#
1,
1!
1*
b11 0
#1825
0#
0,
#1830
1#
1,
0!
0*
b10 0
b11 /
b100 0
#1835
0#
0,
#1840
1#
1,
1!
1*
b0 0
b100 /
1-
b1000 .
1$
#1845
0#
0,
#1850
1#
1,
b0 /
0-
0$
#1855
0#
0,
#1860
1#
1,
0!
0*
b1 0
#1865
0#
0,
#1870
1#
1,
b1 /
b10 0
#1875
0#
0,
#1880
1#
1,
b10 /
#1885
0#
0,
#1890
1#
1,
#1895
0#
0,
#1900
1#
1,
1!
1*
b11 0
#1905
0#
0,
#1910
1#
1,
0!
0*
b10 0
b11 /
b100 0
#1915
0#
0,
#1920
1#
1,
b100 /
b10 0
#1925
0#
0,
#1930
1#
1,
b10 /
#1935
0#
0,
#1940
1#
1,
#1945
0#
0,
#1950
1#
1,
1!
1*
b11 0
#1955
0#
0,
#1960
1#
1,
b11 /
b0 0
#1965
0#
0,
#1970
1#
1,
b0 /
#1975
0#
0,
#1980
1#
1,
0!
0*
b1 0
#1985
0#
0,
#1990
1#
1,
1!
1*
b0 0
b1 /
#1995
0#
0,
#2000
1#
1,
b0 /
#2005
0#
0,
#2010
1#
1,
#2015
0#
0,
#2020
1#
1,
0!
0*
b1 0
#2025
0#
0,
#2030
1#
1,
b1 /
b10 0
#2035
0#
0,
#2040
1#
1,
1!
1*
b0 0
b10 /
b11 0
#2045
0#
0,
#2050
1#
1,
b11 /
b0 0
#2055
0#
0,
#2060
1#
1,
b0 /
#2065
0#
0,
#2070
1#
1,
#2075
0#
0,
#2080
1#
1,
#2085
0#
0,
#2090
1#
1,
0!
0*
b1 0
#2095
0#
0,
#2100
1#
1,
1!
1*
b0 0
b1 /
#2105
0#
0,
#2110
1#
1,
b0 /
#2115
0#
0,
#2120
1#
1,
0!
0*
b1 0
#2125
0#
0,
#2130
1#
1,
b1 /
b10 0
#2135
0#
0,
#2140
1#
1,
b10 /
#2145
0#
0,
#2150
1#
1,
#2155
0#
0,
#2160
1#
1,
1!
1*
b11 0
#2165
0#
0,
#2170
1#
1,
b11 /
b0 0
#2175
0#
0,
#2180
1#
1,
0!
0*
b100 0
b0 /
b1 0
#2185
0#
0,
#2190
1#
1,
b1 /
b10 0
#2195
0#
0,
#2200
1#
1,
1!
1*
b0 0
b10 /
b11 0
#2205
0#
0,
#2210
1#
1,
0!
0*
b10 0
b11 /
b100 0
#2215
0#
0,
#2220
1#
1,
b100 /
b10 0
#2225
0#
0,
#2230
1#
1,
1!
1*
b0 0
1-
b1001 .
1$
b10 /
b11 0
0-
0$
#2235
0#
0,
#2240
1#
1,
0!
0*
b10 0
b11 /
b100 0
#2245
0#
0,
#2250
1#
1,
b100 /
b10 0
#2255
0#
0,
#2260
1#
1,
1!
1*
b0 0
1-
b1010 .
1$
b10 /
b11 0
0-
0$
#2265
0#
0,
#2270
1#
1,
0!
0*
b10 0
b11 /
b100 0
#2275
0#
0,
#2280
1#
1,
b100 /
b10 0
#2285
0#
0,
#2290
1#
1,
1!
1*
b0 0
1-
b1011 .
1$
b10 /
b11 0
0-
0$
#2295
0#
0,
#2300
1#
1,
b11 /
b0 0
#2305
0#
0,
#2310
1#
1,
b0 /
#2315
0#
0,
#2320
1#
1,
0!
0*
b1 0
#2325
0#
0,
#2330
1#
1,
b1 /
b10 0
#2335
0#
0,
#2340
1#
1,
b10 /
#2345
0#
0,
#2350
1#
1,
1!
1*
b11 0
#2355
0#
0,
#2360
1#
1,
0!
0*
b10 0
b11 /
b100 0
#2365
0#
0,
#2370
1#
1,
b100 /
b10 0
#2375
0#
0,
#2380
1#
1,
1!
1*
b0 0
1-
b1100 .
1$
b10 /
b11 0
0-
0$
#2385
0#
0,
#2390
1#
1,
0!
0*
b10 0
b11 /
b100 0
#2395
0#
0,
#2400
1#
1,
b100 /
b10 0
#2405
0#
0,
#2410
1#
1,
b10 /
#2415
0#
0,
#2420
1#
1,
#2425
0#
0,
#2430
1#
1,
1!
1*
b11 0
#2435
0#
0,
#2440
1#
1,
0!
0*
b10 0
b11 /
b100 0
#2445
0#
0,
#2450
1#
1,
b100 /
b10 0
#2455
0#
0,
#2460
1#
1,
b10 /
#2465
0#
0,
#2470
1#
1,
1!
1*
b11 0
#2475
0#
0,
#2480
1#
1,
b11 /
b0 0
#2485
0#
0,
#2490
1#
1,
0!
0*
b100 0
b0 /
b1 0
#2495
0#
0,
#2500
1#
1,
1!
1*
b0 0
b1 /
#2505
0#
0,
#2510
1#
1,
b0 /
#2515
0#
0,
#2520
1#
1,
#2525
0#
0,
#2530
1#
1,
#2535
0#
0,
#2540
1#
1,
0!
0*
b1 0
#2545
0#
0,
#2550
1#
1,
1!
1*
b0 0
b1 /
#2555
0#
0,
#2560
1#
1,
b0 /
#2565
0#
0,
#2570
1#
1,
#2575
0#
0,
#2580
1#
1,
0!
0*
b1 0
#2585
0#
0,
#2590
1#
1,
b1 /
b10 0
#2595
0#
0,
#2600
1#
1,
1!
1*
b0 0
b10 /
b11 0
#2605
0#
0,
#2610
1#
1,
0!
0*
b10 0
b11 /
b100 0
#2615
0#
0,
#2620
1#
1,
b100 /
b10 0
#2625
0#
0,
#2630
1#
1,
1!
1*
b0 0
1-
b1101 .
1$
b10 /
b11 0
0-
0$
#2635
0#
0,
#2640
1#
1,
b11 /
b0 0
#2645
0#
0,
#2650
1#
1,
0!
0*
b100 0
b0 /
b1 0
#2655
0#
0,
#2660
1#
1,
b1 /
b10 0
#2665
0#
0,
#2670
1#
1,
1!
1*
b0 0
b10 /
b11 0
#2675
0#
0,
#2680
1#
1,
0!
0*
b10 0
b11 /
b100 0
#2685
0#
0,
#2690
1#
1,
b100 /
b10 0
#2695
0#
0,
#2700
1#
1,
1!
1*
b0 0
1-
b1110 .
1$
b10 /
b11 0
0-
0$
#2705
0#
0,
#2710
1#
1,
0!
0*
b10 0
b11 /
b100 0
#2715
0#
0,
#2720
1#
1,
1!
1*
b0 0
b100 /
1-
b1111 .
1$
#2725
0#
0,
#2730
1#
1,
b0 /
0-
0$
#2735
0#
0,
#2740
1#
1,
0!
0*
b1 0
#2745
0#
0,
#2750
1#
1,
1!
1*
b0 0
b1 /
#2755
0#
0,
#2760
1#
1,
0!
0*
b10 0
b0 /
b1 0
#2765
0#
0,
#2770
1#
1,
1!
1*
b0 0
b1 /
#2775
0#
0,
#2780
1#
1,
0!
0*
b10 0
b0 /
b1 0
#2785
0#
0,
#2790
1#
1,
b1 /
b10 0
#2795
0#
0,
#2800
1#
1,
1!
1*
b0 0
b10 /
b11 0
#2805
0#
0,
#2810
1#
1,
0!
0*
b10 0
b11 /
b100 0
#2815
0#
0,
#2820
1#
1,
b100 /
b10 0
#2825
0#
0,
#2830
1#
1,
b10 /
#2835
0#
0,
#2840
1#
1,
1!
1*
b11 0
#2845
0#
0,
#2850
1#
1,
b11 /
b0 0
#2855
0#
0,
#2860
1#
1,
b0 /
#2865
0#
0,
#2870
1#
1,
#2875
0#
0,
#2880
1#
1,
#2885
0#
0,
#2890
1#
1,
0!
0*
b1 0
#2895
0#
0,
#2900
1#
1,
1!
1*
b0 0
b1 /
#2905
0#
0,
#2910
1#
1,
b0 /
#2915
0#
0,
#2920
1#
1,
#2925
0#
0,
#2930
1#
1,
0!
0*
b1 0
#2935
0#
0,
#2940
1#
1,
b1 /
b10 0
#2945
0#
0,
#2950
1#
1,
b10 /
#2955
0#
0,
#2960
1#
1,
#2965
0#
0,
#2970
1#
1,
#2975
0#
0,
#2980
1#
1,
#2985
0#
0,
#2990
1#
1,
1!
1*
b11 0
#2995
0#
0,
#3000
1#
1,
b11 /
b0 0
#3005
0#
0,
#3010
1#
1,
b0 /
#3015
0#
0,
#3020
1#
1,
#3025
0#
0,
#3030
1#
1,
#3035
0#
0,
#3040
1#
1,
#3045
0#
0,
#3050
1#
1,
#3055
0#
0,
#3060
1#
1,
0!
0*
b1 0
#3065
0#
0,
#3070
1#
1,
1!
1*
b0 0
b1 /
#3075
0#
0,
#3080
1#
1,
b0 /
#3085
0#
0,
#3090
1#
1,
#3095
0#
0,
#3100
1#
1,
#3105
0#
0,
#3110
1#
1,
#3115
0#
0,
#3120
1#
1,
#3125
0#
0,
#3130
1#
1,
#3135
0#
0,
#3140
1#
1,
#3145
0#
0,
#3150
1#
1,
0!
0*
b1 0
#3155
0#
0,
#3160
1#
1,
b1 /
b10 0
#3165
0#
0,
#3170
1#
1,
1!
1*
b0 0
b10 /
b11 0
#3175
0#
0,
#3180
1#
1,
b11 /
b0 0
#3185
0#
0,
#3190
1#
1,
0!
0*
b100 0
b0 /
b1 0
#3195
0#
0,
#3200
1#
1,
b1 /
b10 0
#3205
0#
0,
#3210
1#
1,
b10 /
#3215
0#
0,
#3220
1#
1,
#3225
0#
0,
#3230
1#
1,
1!
1*
b11 0
#3235
0#
0,
#3240
1#
1,
0!
0*
b10 0
b11 /
b100 0
#3245
0#
0,
#3250
1#
1,
b100 /
b10 0
#3255
0#
0,
#3260
1#
1,
b10 /
#3265
0#
0,
#3270
1#
1,
#3275
0#
0,
#3280
1#
1,
#3285
0#
0,
#3290
1#
1,
#3295
0#
0,
#3300
1#
1,
1!
1*
b11 0
#3305
0#
0,
#3310
1#
1,
0!
0*
b10 0
b11 /
b100 0
#3315
0#
0,
#3320
1#
1,
b100 /
b10 0
#3325
0#
0,
#3330
1#
1,
1!
1*
b0 0
1-
b10000 .
1$
b10 /
b11 0
0-
0$
#3335
0#
0,
#3340
1#
1,
0!
0*
b10 0
b11 /
b100 0
#3345
0#
0,
#3350
1#
1,
b100 /
b10 0
#3355
0#
0,
#3360
1#
1,
b10 /
#3365
0#
0,
#3370
1#
1,
#3375
0#
0,
#3380
1#
1,
1!
1*
b11 0
#3385
0#
0,
#3390
1#
1,
b11 /
b0 0
#3395
0#
0,
#3400
1#
1,
b0 /
#3405
0#
0,
#3410
1#
1,
#3415
0#
0,
#3420
1#
1,
#3425
0#
0,
#3430
1#
1,
0!
0*
b1 0
#3435
0#
0,
#3440
1#
1,
1!
1*
b0 0
b1 /
#3445
0#
0,
#3450
1#
1,
b0 /
#3455
0#
0,
#3460
1#
1,
#3465
0#
0,
#3470
1#
1,
0!
0*
b1 0
#3475
0#
0,
#3480
1#
1,
1!
1*
b0 0
b1 /
#3485
0#
0,
#3490
1#
1,
0!
0*
b10 0
b0 /
b1 0
#3495
0#
0,
#3500
1#
1,
b1 /
b10 0
#3505
0#
0,
#3510
1#
1,
1!
1*
b0 0
b10 /
b11 0
#3515
0#
0,
#3520
1#
1,
b11 /
b0 0
#3525
0#
0,
#3530
1#
1,
0!
0*
b100 0
b0 /
b1 0
#3535
0#
0,
#3540
1#
1,
1!
1*
b0 0
b1 /
#3545
0#
0,
#3550
1#
1,
0!
0*
b10 0
b0 /
b1 0
#3555
0#
0,
#3560
1#
1,
b1 /
b10 0
#3565
0#
0,
#3570
1#
1,
1!
1*
b0 0
b10 /
b11 0
#3575
0#
0,
#3580
1#
1,
0!
0*
b10 0
b11 /
b100 0
#3585
0#
0,
#3590
1#
1,
b100 /
b10 0
#3595
0#
0,
#3600
1#
1,
b10 /
#3605
0#
0,
#3610
1#
1,
#3615
0#
0,
#3620
1#
1,
1!
1*
b11 0
#3625
0#
0,
#3630
1#
1,
b11 /
b0 0
#3635
0#
0,
#3640
1#
1,
b0 /
#3645
0#
0,
#3650
1#
1,
#3655
0#
0,
#3660
1#
1,
0!
0*
b1 0
#3665
0#
0,
#3670
1#
1,
1!
1*
b0 0
b1 /
#3675
0#
0,
#3680
1#
1,
b0 /
#3685
0#
0,
#3690
1#
1,
#3695
0#
0,
#3700
1#
1,
#3705
0#
0,
#3710
1#
1,
#3715
0#
0,
#3720
1#
1,
#3725
0#
0,
#3730
1#
1,
#3735
0#
0,
#3740
1#
1,
0!
0*
b1 0
#3745
0#
0,
#3750
1#
1,
1!
1*
b0 0
b1 /
#3755
0#
0,
#3760
1#
1,
0!
0*
b10 0
b0 /
b1 0
#3765
0#
0,
#3770
1#
1,
1!
1*
b0 0
b1 /
#3775
0#
0,
#3780
1#
1,
0!
0*
b10 0
b0 /
b1 0
#3785
0#
0,
#3790
1#
1,
b1 /
b10 0
#3795
0#
0,
#3800
1#
1,
1!
1*
b0 0
b10 /
b11 0
#3805
0#
0,
#3810
1#
1,
0!
0*
b10 0
b11 /
b100 0
#3815
0#
0,
#3820
1#
1,
b100 /
b10 0
#3825
0#
0,
#3830
1#
1,
b10 /
#3835
0#
0,
#3840
1#
1,
#3845
0#
0,
#3850
1#
1,
#3855
0#
0,
#3860
1#
1,
1!
1*
b11 0
#3865
0#
0,
#3870
1#
1,
0!
0*
b10 0
b11 /
b100 0
#3875
0#
0,
#3880
1#
1,
b100 /
b10 0
#3885
0#
0,
#3890
1#
1,
b10 /
#3895
0#
0,
#3900
1#
1,
#3905
0#
0,
#3910
1#
1,
#3915
0#
0,
#3920
1#
1,
#3925
0#
0,
#3930
1#
1,
1!
1*
b11 0
#3935
0#
0,
#3940
1#
1,
0!
0*
b10 0
b11 /
b100 0
#3945
0#
0,
#3950
1#
1,
1!
1*
b0 0
b100 /
1-
b10001 .
1$
#3955
0#
0,
#3960
1#
1,
0!
0*
b10 0
0-
0$
b0 /
b1 0
#3965
0#
0,
#3970
1#
1,
b1 /
b10 0
#3975
0#
0,
#3980
1#
1,
1!
1*
b0 0
b10 /
b11 0
#3985
0#
0,
#3990
1#
1,
0!
0*
b10 0
b11 /
b100 0
#3995
0#
0,
#4000
1#
1,
1!
1*
b0 0
b100 /
1-
b10010 .
1$
#4005
0#
0,
#4010
1#
1,
b0 /
0-
0$
#4015
0#
0,
#4020
1#
1,
0!
0*
b1 0
#4025
0#
0,
#4030
1#
1,
1!
1*
b0 0
b1 /
#4035
0#
0,
#4040
1#
1,
0!
0*
b10 0
b0 /
b1 0
#4045
0#
0,
#4050
1#
1,
1!
1*
b0 0
b1 /
#4055
0#
0,
#4060
1#
1,
0!
0*
b10 0
b0 /
b1 0
#4065
0#
0,
#4070
1#
1,
b1 /
b10 0
#4075
0#
0,
#4080
1#
1,
b10 /
#4085
0#
0,
#4090
1#
1,
#4095
0#
0,
#4100
1#
1,
1!
1*
b11 0
#4105
0#
0,
#4110
1#
1,
0!
0*
b10 0
b11 /
b100 0
#4115
0#
0,
#4120
1#
1,
1!
1*
b0 0
b100 /
1-
b10011 .
1$
#4125
0#
0,
#4130
1#
1,
0!
0*
b10 0
0-
0$
b0 /
b1 0
#4135
0#
0,
#4140
1#
1,
1!
1*
b0 0
b1 /
#4145
0#
0,
#4150
1#
1,
b0 /
#4155
0#
0,
#4160
1#
1,
0!
0*
b1 0
#4165
0#
0,
#4170
1#
1,
1!
1*
b0 0
b1 /
#4175
0#
0,
#4180
1#
1,
0!
0*
b10 0
b0 /
b1 0
#4185
0#
0,
#4190
1#
1,
1!
1*
b0 0
b1 /
#4195
0#
0,
#4200
1#
1,
b0 /
#4205
0#
0,
#4210
1#
1,
#4215
0#
0,
#4220
1#
1,
0!
0*
b1 0
#4225
0#
0,
#4230
1#
1,
1!
1*
b0 0
b1 /
#4235
0#
0,
#4240
1#
1,
b0 /
#4245
0#
0,
#4250
1#
1,
0!
0*
b1 0
#4255
0#
0,
#4260
1#
1,
b1 /
b10 0
#4265
0#
0,
#4270
1#
1,
1!
1*
b0 0
b10 /
b11 0
#4275
0#
0,
#4280
1#
1,
b11 /
b0 0
#4285
0#
0,
#4290
1#
1,
0!
0*
b100 0
b0 /
b1 0
#4295
0#
0,
#4300
1#
1,
b1 /
b10 0
#4305
0#
0,
#4310
1#
1,
1!
1*
b0 0
b10 /
b11 0
#4315
0#
0,
#4320
1#
1,
b11 /
b0 0
#4325
0#
0,
#4330
1#
1,
0!
0*
b100 0
b0 /
b1 0
#4335
0#
0,
#4340
1#
1,
b1 /
b10 0
#4345
0#
0,
#4350
1#
1,
1!
1*
b0 0
b10 /
b11 0
#4355
0#
0,
#4360
1#
1,
0!
0*
b10 0
b11 /
b100 0
#4365
0#
0,
#4370
1#
1,
b100 /
b10 0
#4375
0#
0,
#4380
1#
1,
1!
1*
b0 0
1-
b10100 .
1$
b10 /
b11 0
0-
0$
#4385
0#
0,
#4390
1#
1,
b11 /
b0 0
#4395
0#
0,
#4400
1#
1,
0!
0*
b100 0
b0 /
b1 0
#4405
0#
0,
#4410
1#
1,
b1 /
b10 0
#4415
0#
0,
#4420
1#
1,
1!
1*
b0 0
b10 /
b11 0
#4425
0#
0,
#4430
1#
1,
0!
0*
b10 0
b11 /
b100 0
#4435
0#
0,
#4440
1#
1,
b100 /
b10 0
#4445
0#
0,
#4450
1#
1,
1!
1*
b0 0
1-
b10101 .
1$
b10 /
b11 0
0-
0$
#4455
0#
0,
#4460
1#
1,
b11 /
b0 0
#4465
0#
0,
#4470
1#
1,
0!
0*
b100 0
b0 /
b1 0
#4475
0#
0,
#4480
1#
1,
1!
1*
b0 0
b1 /
