Master/6_sequentialmemory/memory2.v
module memory (clk, rst, addr, wdata,wrbar, rdata,valid, ready);

parameter WIDTH=32;
parameter DEPTH=256;
parameter ADDR=8;



input clk, rst, wrbar, valid;
input [ADDR-1:0] addr;
input [WIDTH-1:0] wdata;
output reg [WIDTH-1:0] rdata;
output reg ready;
integer i;


reg [WIDTH-1:0] mem [DEPTH-1:0];



always @(posedge clk) begin
if(rst) begin 
	rdata=0;
	ready=0;
	for (i=0; i<DEPTH; i=i+1) mem[i]=0;
	end

else begin // we dont need a for loop here because the user will provide the value of address and wrbar value

if (valid) begin
ready=1;
if (wrbar==1) mem[addr]=wdata;
else rdata=mem[addr];
end


else begin
ready=0;
end
end
end
endmodule

Master/6_sequentialmemory/memory2_tb2.v
`include"memory2.v"
module tb();

parameter WIDTH=32;
parameter DEPTH=256;
parameter ADDR=8;


reg clk, rst, wrbar, valid;
reg [ADDR-1:0] addr;
reg [WIDTH-1:0] wdata;
wire [WIDTH-1:0] rdata;
wire ready;
integer i;
reg[30*8:1] testname;  //testcase variable
  
  memory #(.WIDTH(WIDTH),.DEPTH(DEPTH), .ADDR(ADDR)) dut(clk, rst, addr, wdata,wrbar, rdata,valid,ready); //PARAMETER OVERRIDING FACILITY


//clock generation

initial begin 
$value$plusargs("testname=%s",testname);
clk=0;
forever #5 clk=~clk;
end

initial begin
rst=1;
#20;
rst=0;

case(testname)
"fd_wr_rd_by8": begin
fd_wr_mem(0, DEPTH/8);
fd_rd_mem(0, DEPTH/8);

end

"fd_wr_rd_by4": begin
fd_wr_mem(0, DEPTH/4);
fd_rd_mem(0, DEPTH/4);

end
"fd_wr_rd_by2": begin
fd_wr_mem(0, DEPTH/2);
fd_rd_mem(0, DEPTH/2);

end
"fd_wr_rd_by1": begin
fd_wr_mem(0, DEPTH);
fd_rd_mem(0, DEPTH);

end
  
  endcase

#100 $finish;
end
initial begin
  $dumpvars;
  $dumpfile("dump.vcd");
  
end
// task to write to memory at some specific locations starting from start_addr and till number of locations = num_loc
  task fd_wr_mem(input [ADDR-1:0]start_loc, [ADDR:0]num_loc);
begin
//wrbar=1;
for (i=start_loc;i<start_loc+num_loc;i=i+1) begin
@(posedge clk);
addr=i;
wdata=$random;
wrbar=1;
valid=1;
wait(ready==1);
end

//@(posedge clk);
wrbar=0;
valid=0;
addr=0;
wdata=0;
end
endtask

// task to read memory at some specific locations starting from start_addr and till number of locations = num_loc

  task fd_rd_mem(input [ADDR-1:0]start_loc, [ADDR:0]num_loc);
begin
//wrbar=1;
for (i=start_loc;i<start_loc+num_loc;i=i+1) begin
@(posedge clk);
addr=i;
wrbar=0;
valid=1;
wait(ready==1);
end

//@(posedge clk);
wrbar=0; //check that it shud be toggled or not
valid=0;
addr=0;
wdata=0;
end
endtask

initial begin
  $dumpfile("dump.vcd");
  $dumpvars;
  
end

endmodule

Master/6_sequentialmemory/dump.vcd
$date
	Sat Oct  9 13:29:28 2021
$end
$version
	ModelSim Version 2021.1
$end
$timescale
	1ps
$end

$scope module tb $end
$var parameter 32 ! WIDTH $end
$var parameter 32 " DEPTH $end
$var parameter 32 # ADDR $end
$var reg 1 $ clk $end
$var reg 1 % rst $end
$var reg 1 & wrbar $end
$var reg 1 ' valid $end
$var reg 8 ( addr [7:0] $end
$var reg 32 ) wdata [31:0] $end
$var wire 1 * rdata [31] $end
$var wire 1 + rdata [30] $end
$var wire 1 , rdata [29] $end
$var wire 1 - rdata [28] $end
$var wire 1 . rdata [27] $end
$var wire 1 / rdata [26] $end
$var wire 1 0 rdata [25] $end
$var wire 1 1 rdata [24] $end
$var wire 1 2 rdata [23] $end
$var wire 1 3 rdata [22] $end
$var wire 1 4 rdata [21] $end
$var wire 1 5 rdata [20] $end
$var wire 1 6 rdata [19] $end
$var wire 1 7 rdata [18] $end
$var wire 1 8 rdata [17] $end
$var wire 1 9 rdata [16] $end
$var wire 1 : rdata [15] $end
$var wire 1 ; rdata [14] $end
$var wire 1 < rdata [13] $end
$var wire 1 = rdata [12] $end
$var wire 1 > rdata [11] $end
$var wire 1 ? rdata [10] $end
$var wire 1 @ rdata [9] $end
$var wire 1 A rdata [8] $end
$var wire 1 B rdata [7] $end
$var wire 1 C rdata [6] $end
$var wire 1 D rdata [5] $end
$var wire 1 E rdata [4] $end
$var wire 1 F rdata [3] $end
$var wire 1 G rdata [2] $end
$var wire 1 H rdata [1] $end
$var wire 1 I rdata [0] $end
$var wire 1 J ready $end
$var integer 32 K i $end
$var reg 240 L testname [240:1] $end

$scope task fd_wr_mem $end
$var reg 8 M start_loc [7:0] $end
$var reg 9 N num_loc [8:0] $end
$upscope $end

$scope task fd_rd_mem $end
$var reg 8 O start_loc [7:0] $end
$var reg 9 P num_loc [8:0] $end
$upscope $end

$scope module dut $end
$var parameter 32 Q WIDTH $end
$var parameter 32 R DEPTH $end
$var parameter 32 S ADDR $end
$var wire 1 T clk $end
$var wire 1 U rst $end
$var wire 1 V wrbar $end
$var wire 1 W valid $end
$var wire 1 X addr [7] $end
$var wire 1 Y addr [6] $end
$var wire 1 Z addr [5] $end
$var wire 1 [ addr [4] $end
$var wire 1 \ addr [3] $end
$var wire 1 ] addr [2] $end
$var wire 1 ^ addr [1] $end
$var wire 1 _ addr [0] $end
$var wire 1 ` wdata [31] $end
$var wire 1 a wdata [30] $end
$var wire 1 b wdata [29] $end
$var wire 1 c wdata [28] $end
$var wire 1 d wdata [27] $end
$var wire 1 e wdata [26] $end
$var wire 1 f wdata [25] $end
$var wire 1 g wdata [24] $end
$var wire 1 h wdata [23] $end
$var wire 1 i wdata [22] $end
$var wire 1 j wdata [21] $end
$var wire 1 k wdata [20] $end
$var wire 1 l wdata [19] $end
$var wire 1 m wdata [18] $end
$var wire 1 n wdata [17] $end
$var wire 1 o wdata [16] $end
$var wire 1 p wdata [15] $end
$var wire 1 q wdata [14] $end
$var wire 1 r wdata [13] $end
$var wire 1 s wdata [12] $end
$var wire 1 t wdata [11] $end
$var wire 1 u wdata [10] $end
$var wire 1 v wdata [9] $end
$var wire 1 w wdata [8] $end
$var wire 1 x wdata [7] $end
$var wire 1 y wdata [6] $end
$var wire 1 z wdata [5] $end
$var wire 1 { wdata [4] $end
$var wire 1 | wdata [3] $end
$var wire 1 } wdata [2] $end
$var wire 1 ~ wdata [1] $end
$var wire 1 !! wdata [0] $end
$var reg 32 "! rdata [31:0] $end
$var reg 1 #! ready $end
$var integer 32 $! i $end
$upscope $end
$var wire 1 * rdata [31] $end
$var wire 1 + rdata [30] $end
$var wire 1 , rdata [29] $end
$var wire 1 - rdata [28] $end
$var wire 1 . rdata [27] $end
$var wire 1 / rdata [26] $end
$var wire 1 0 rdata [25] $end
$var wire 1 1 rdata [24] $end
$var wire 1 2 rdata [23] $end
$var wire 1 3 rdata [22] $end
$var wire 1 4 rdata [21] $end
$var wire 1 5 rdata [20] $end
$var wire 1 6 rdata [19] $end
$var wire 1 7 rdata [18] $end
$var wire 1 8 rdata [17] $end
$var wire 1 9 rdata [16] $end
$var wire 1 : rdata [15] $end
$var wire 1 ; rdata [14] $end
$var wire 1 < rdata [13] $end
$var wire 1 = rdata [12] $end
$var wire 1 > rdata [11] $end
$var wire 1 ? rdata [10] $end
$var wire 1 @ rdata [9] $end
$var wire 1 A rdata [8] $end
$var wire 1 B rdata [7] $end
$var wire 1 C rdata [6] $end
$var wire 1 D rdata [5] $end
$var wire 1 E rdata [4] $end
$var wire 1 F rdata [3] $end
$var wire 1 G rdata [2] $end
$var wire 1 H rdata [1] $end
$var wire 1 I rdata [0] $end
$var wire 1 J ready $end

$scope task fd_wr_mem $end
$upscope $end

$scope task fd_rd_mem $end
$upscope $end

$scope module dut $end
$var wire 1 T clk $end
$var wire 1 U rst $end
$var wire 1 V wrbar $end
$var wire 1 W valid $end
$var wire 1 X addr [7] $end
$var wire 1 Y addr [6] $end
$var wire 1 Z addr [5] $end
$var wire 1 [ addr [4] $end
$var wire 1 \ addr [3] $end
$var wire 1 ] addr [2] $end
$var wire 1 ^ addr [1] $end
$var wire 1 _ addr [0] $end
$var wire 1 ` wdata [31] $end
$var wire 1 a wdata [30] $end
$var wire 1 b wdata [29] $end
$var wire 1 c wdata [28] $end
$var wire 1 d wdata [27] $end
$var wire 1 e wdata [26] $end
$var wire 1 f wdata [25] $end
$var wire 1 g wdata [24] $end
$var wire 1 h wdata [23] $end
$var wire 1 i wdata [22] $end
$var wire 1 j wdata [21] $end
$var wire 1 k wdata [20] $end
$var wire 1 l wdata [19] $end
$var wire 1 m wdata [18] $end
$var wire 1 n wdata [17] $end
$var wire 1 o wdata [16] $end
$var wire 1 p wdata [15] $end
$var wire 1 q wdata [14] $end
$var wire 1 r wdata [13] $end
$var wire 1 s wdata [12] $end
$var wire 1 t wdata [11] $end
$var wire 1 u wdata [10] $end
$var wire 1 v wdata [9] $end
$var wire 1 w wdata [8] $end
$var wire 1 x wdata [7] $end
$var wire 1 y wdata [6] $end
$var wire 1 z wdata [5] $end
$var wire 1 { wdata [4] $end
$var wire 1 | wdata [3] $end
$var wire 1 } wdata [2] $end
$var wire 1 ~ wdata [1] $end
$var wire 1 !! wdata [0] $end
$upscope $end
$upscope $end
$enddefinitions $end
#0
$dumpvars
0$
1%
x&
x'
bx (
bx )
b11001100110010001011111011101110111001001011111011100100110010001011111011000100111100100110100 L
bx "!
x#!
bx M
bx N
bx O
bx P
b100000 !
b100000000 "
b1000 #
b100000 Q
b100000000 R
b1000 S
bx K
bx $!
xI
xH
xG
xF
xE
xD
xC
xB
xA
x@
x?
x>
x=
x<
x;
x:
x9
x8
x7
x6
x5
x4
x3
x2
x1
x0
x/
x.
x-
x,
x+
x*
xJ
xW
xV
x!!
x~
x}
x|
x{
xz
xy
xx
xw
xv
xu
xt
xs
xr
xq
xp
xo
xn
xm
xl
xk
xj
xi
xh
xg
xf
xe
xd
xc
xb
xa
x`
x_
x^
x]
x\
x[
xZ
xY
xX
1U
0T
$end
#5
1$
1T
b0 "!
0#!
b0 $!
b1 $!
b10 $!
b11 $!
b100 $!
b101 $!
b110 $!
b111 $!
b1000 $!
b1001 $!
b1010 $!
b1011 $!
b1100 $!
b1101 $!
b1110 $!
b1111 $!
b10000 $!
b10001 $!
b10010 $!
b10011 $!
b10100 $!
b10101 $!
b10110 $!
b10111 $!
b11000 $!
b11001 $!
b11010 $!
b11011 $!
b11100 $!
b11101 $!
b11110 $!
b11111 $!
b100000 $!
b100001 $!
b100010 $!
b100011 $!
b100100 $!
b100101 $!
b100110 $!
b100111 $!
b101000 $!
b101001 $!
b101010 $!
b101011 $!
b101100 $!
b101101 $!
b101110 $!
b101111 $!
b110000 $!
b110001 $!
b110010 $!
b110011 $!
b110100 $!
b110101 $!
b110110 $!
b110111 $!
b111000 $!
b111001 $!
b111010 $!
b111011 $!
b111100 $!
b111101 $!
b111110 $!
b111111 $!
b1000000 $!
b1000001 $!
b1000010 $!
b1000011 $!
b1000100 $!
b1000101 $!
b1000110 $!
b1000111 $!
b1001000 $!
b1001001 $!
b1001010 $!
b1001011 $!
b1001100 $!
b1001101 $!
b1001110 $!
b1001111 $!
b1010000 $!
b1010001 $!
b1010010 $!
b1010011 $!
b1010100 $!
b1010101 $!
b1010110 $!
b1010111 $!
b1011000 $!
b1011001 $!
b1011010 $!
b1011011 $!
b1011100 $!
b1011101 $!
b1011110 $!
b1011111 $!
b1100000 $!
b1100001 $!
b1100010 $!
b1100011 $!
b1100100 $!
b1100101 $!
b1100110 $!
b1100111 $!
b1101000 $!
b1101001 $!
b1101010 $!
b1101011 $!
b1101100 $!
b1101101 $!
b1101110 $!
b1101111 $!
b1110000 $!
b1110001 $!
b1110010 $!
b1110011 $!
b1110100 $!
b1110101 $!
b1110110 $!
b1110111 $!
b1111000 $!
b1111001 $!
b1111010 $!
b1111011 $!
b1111100 $!
b1111101 $!
b1111110 $!
b1111111 $!
b10000000 $!
b10000001 $!
b10000010 $!
b10000011 $!
b10000100 $!
b10000101 $!
b10000110 $!
b10000111 $!
b10001000 $!
b10001001 $!
b10001010 $!
b10001011 $!
b10001100 $!
b10001101 $!
b10001110 $!
b10001111 $!
b10010000 $!
b10010001 $!
b10010010 $!
b10010011 $!
b10010100 $!
b10010101 $!
b10010110 $!
b10010111 $!
b10011000 $!
b10011001 $!
b10011010 $!
b10011011 $!
b10011100 $!
b10011101 $!
b10011110 $!
b10011111 $!
b10100000 $!
b10100001 $!
b10100010 $!
b10100011 $!
b10100100 $!
b10100101 $!
b10100110 $!
b10100111 $!
b10101000 $!
b10101001 $!
b10101010 $!
b10101011 $!
b10101100 $!
b10101101 $!
b10101110 $!
b10101111 $!
b10110000 $!
b10110001 $!
b10110010 $!
b10110011 $!
b10110100 $!
b10110101 $!
b10110110 $!
b10110111 $!
b10111000 $!
b10111001 $!
b10111010 $!
b10111011 $!
b10111100 $!
b10111101 $!
b10111110 $!
b10111111 $!
b11000000 $!
b11000001 $!
b11000010 $!
b11000011 $!
b11000100 $!
b11000101 $!
b11000110 $!
b11000111 $!
b11001000 $!
b11001001 $!
b11001010 $!
b11001011 $!
b11001100 $!
b11001101 $!
b11001110 $!
b11001111 $!
b11010000 $!
b11010001 $!
b11010010 $!
b11010011 $!
b11010100 $!
b11010101 $!
b11010110 $!
b11010111 $!
b11011000 $!
b11011001 $!
b11011010 $!
b11011011 $!
b11011100 $!
b11011101 $!
b11011110 $!
b11011111 $!
b11100000 $!
b11100001 $!
b11100010 $!
b11100011 $!
b11100100 $!
b11100101 $!
b11100110 $!
b11100111 $!
b11101000 $!
b11101001 $!
b11101010 $!
b11101011 $!
b11101100 $!
b11101101 $!
b11101110 $!
b11101111 $!
b11110000 $!
b11110001 $!
b11110010 $!
b11110011 $!
b11110100 $!
b11110101 $!
b11110110 $!
b11110111 $!
b11111000 $!
b11111001 $!
b11111010 $!
b11111011 $!
b11111100 $!
b11111101 $!
b11111110 $!
b11111111 $!
b100000000 $!
0I
0H
0G
0F
0E
0D
0C
0B
0A
0@
0?
0>
0=
0<
0;
0:
09
08
07
06
05
04
03
02
01
00
0/
0.
0-
0,
0+
0*
0J
#10
0$
0T
#15
1$
1T
b0 $!
b1 $!
b10 $!
b11 $!
b100 $!
b101 $!
b110 $!
b111 $!
b1000 $!
b1001 $!
b1010 $!
b1011 $!
b1100 $!
b1101 $!
b1110 $!
b1111 $!
b10000 $!
b10001 $!
b10010 $!
b10011 $!
b10100 $!
b10101 $!
b10110 $!
b10111 $!
b11000 $!
b11001 $!
b11010 $!
b11011 $!
b11100 $!
b11101 $!
b11110 $!
b11111 $!
b100000 $!
b100001 $!
b100010 $!
b100011 $!
b100100 $!
b100101 $!
b100110 $!
b100111 $!
b101000 $!
b101001 $!
b101010 $!
b101011 $!
b101100 $!
b101101 $!
b101110 $!
b101111 $!
b110000 $!
b110001 $!
b110010 $!
b110011 $!
b110100 $!
b110101 $!
b110110 $!
b110111 $!
b111000 $!
b111001 $!
b111010 $!
b111011 $!
b111100 $!
b111101 $!
b111110 $!
b111111 $!
b1000000 $!
b1000001 $!
b1000010 $!
b1000011 $!
b1000100 $!
b1000101 $!
b1000110 $!
b1000111 $!
b1001000 $!
b1001001 $!
b1001010 $!
b1001011 $!
b1001100 $!
b1001101 $!
b1001110 $!
b1001111 $!
b1010000 $!
b1010001 $!
b1010010 $!
b1010011 $!
b1010100 $!
b1010101 $!
b1010110 $!
b1010111 $!
b1011000 $!
b1011001 $!
b1011010 $!
b1011011 $!
b1011100 $!
b1011101 $!
b1011110 $!
b1011111 $!
b1100000 $!
b1100001 $!
b1100010 $!
b1100011 $!
b1100100 $!
b1100101 $!
b1100110 $!
b1100111 $!
b1101000 $!
b1101001 $!
b1101010 $!
b1101011 $!
b1101100 $!
b1101101 $!
b1101110 $!
b1101111 $!
b1110000 $!
b1110001 $!
b1110010 $!
b1110011 $!
b1110100 $!
b1110101 $!
b1110110 $!
b1110111 $!
b1111000 $!
b1111001 $!
b1111010 $!
b1111011 $!
b1111100 $!
b1111101 $!
b1111110 $!
b1111111 $!
b10000000 $!
b10000001 $!
b10000010 $!
b10000011 $!
b10000100 $!
b10000101 $!
b10000110 $!
b10000111 $!
b10001000 $!
b10001001 $!
b10001010 $!
b10001011 $!
b10001100 $!
b10001101 $!
b10001110 $!
b10001111 $!
b10010000 $!
b10010001 $!
b10010010 $!
b10010011 $!
b10010100 $!
b10010101 $!
b10010110 $!
b10010111 $!
b10011000 $!
b10011001 $!
b10011010 $!
b10011011 $!
b10011100 $!
b10011101 $!
b10011110 $!
b10011111 $!
b10100000 $!
b10100001 $!
b10100010 $!
b10100011 $!
b10100100 $!
b10100101 $!
b10100110 $!
b10100111 $!
b10101000 $!
b10101001 $!
b10101010 $!
b10101011 $!
b10101100 $!
b10101101 $!
b10101110 $!
b10101111 $!
b10110000 $!
b10110001 $!
b10110010 $!
b10110011 $!
b10110100 $!
b10110101 $!
b10110110 $!
b10110111 $!
b10111000 $!
b10111001 $!
b10111010 $!
b10111011 $!
b10111100 $!
b10111101 $!
b10111110 $!
b10111111 $!
b11000000 $!
b11000001 $!
b11000010 $!
b11000011 $!
b11000100 $!
b11000101 $!
b11000110 $!
b11000111 $!
b11001000 $!
b11001001 $!
b11001010 $!
b11001011 $!
b11001100 $!
b11001101 $!
b11001110 $!
b11001111 $!
b11010000 $!
b11010001 $!
b11010010 $!
b11010011 $!
b11010100 $!
b11010101 $!
b11010110 $!
b11010111 $!
b11011000 $!
b11011001 $!
b11011010 $!
b11011011 $!
b11011100 $!
b11011101 $!
b11011110 $!
b11011111 $!
b11100000 $!
b11100001 $!
b11100010 $!
b11100011 $!
b11100100 $!
b11100101 $!
b11100110 $!
b11100111 $!
b11101000 $!
b11101001 $!
b11101010 $!
b11101011 $!
b11101100 $!
b11101101 $!
b11101110 $!
b11101111 $!
b11110000 $!
b11110001 $!
b11110010 $!
b11110011 $!
b11110100 $!
b11110101 $!
b11110110 $!
b11110111 $!
b11111000 $!
b11111001 $!
b11111010 $!
b11111011 $!
b11111100 $!
b11111101 $!
b11111110 $!
b11111111 $!
b100000000 $!
#20
0%
b0 M
b1000000 N
b0 K
0$
0U
0T
#25
1$
1T
b0 (
b10010000101010011010100100100 )
1&
1'
0!!
0~
1}
0|
0{
1z
0y
0x
1w
0v
1u
0t
1s
1r
0q
0p
1o
0n
1m
0l
1k
0j
0i
0h
0g
1f
0e
0d
1c
0b
0a
0`
0_
0^
0]
0\
0[
0Z
0Y
0X
1V
1W
#30
0$
0T
#35
1$
1T
1#!
1J
b1 K
#40
0$
0T
#45
1$
1T
b1 (
b11000000100010010101111010000001 )
b10 K
1!!
0}
0z
1x
0w
1v
1t
0r
1q
0m
1l
0k
1h
0f
0c
1a
1`
1_
#50
0$
0T
#55
1$
1T
b10 (
b10000100100001001101011000001001 )
b11 K
1|
0x
0t
1p
0o
1m
0l
1e
0a
0_
1^
#60
0$
0T
#65
1$
1T
b11 (
b10110001111100000101011001100011 )
b100 K
1~
0|
1z
1y
0p
0m
1k
1j
1i
1g
0e
1c
1b
1_
#70
0$
0T
#75
1$
1T
b100 (
b110101110010111101100001101 )
b101 K
0~
1}
1|
0z
0y
1w
0u
1t
1r
1o
1l
0i
0g
1f
1e
0c
0b
0`
0_
0^
1]
#80
0$
0T
#85
1$
1T
b101 (
b1000110110111111001100110001101 )
b110 K
1x
0v
0r
0q
1p
1n
1m
0j
1i
1a
1_
#90
0$
0T
#95
1$
1T
b110 (
b10110010110000101000010001100101 )
b111 K
0|
1z
1y
0x
0w
1u
0t
0s
0o
0m
0l
0k
0e
1c
1b
0a
1`
0_
1^
#100
0$
0T
#105
1$
1T
b111 (
b10001001001101110101001000010010 )
b1000 K
0!!
1~
0}
1{
0z
0y
1v
0u
1s
1q
0p
1o
1m
1k
1j
0i
0h
1g
0f
1d
0c
0b
1_
#110
0$
0T
#115
1$
1T
b1000 (
b111100111110001100000001 )
b1001 K
1!!
0~
0{
1w
0s
1r
1p
0m
1i
1h
0g
0d
0`
0_
0^
0]
1\
#120
0$
0T
#125
1$
1T
b1001 (
b110110101111100110100001101 )
b1010 K
1}
1|
0v
1u
1t
0r
1m
0j
1f
1e
1_
#130
0$
0T
#135
1$
1T
b1010 (
b111011001000111111000101110110 )
b1011 K
0!!
1~
0|
1{
1z
1y
0u
0t
1s
1r
0m
0k
1j
0i
0h
1g
0e
1d
1c
1b
0_
1^
#140
0$
0T
#145
1$
1T
b1011 (
b11110100011011100110100111101 )
b1100 K
1!!
0~
1|
0y
1u
1t
0s
0r
0n
1m
1l
0j
1h
0g
1e
0b
1_
#150
0$
0T
#155
1$
1T
b1100 (
b1110110110101000101011111101101 )
b1101 K
0{
1y
1x
1v
0t
1s
0p
0o
0l
1k
1i
0d
1b
1a
0_
0^
1]
#160
0$
0T
#165
1$
1T
b1101 (
b1000110001011011111011110001100 )
b1110 K
0!!
0z
0y
1r
1p
1o
1l
0k
1j
0i
0h
0c
0b
1_
#170
0$
0T
#175
1$
1T
b1110 (
b1111100111111011110100111111001 )
b1111 K
1!!
0}
1{
1z
1y
0v
0u
1t
0s
1k
1i
1h
0f
1d
1c
1b
0_
1^
#180
0$
0T
#185
1$
1T
b1111 (
b11100011001101110010010011000110 )
b10000 K
0!!
1~
1}
0|
0{
0z
0w
1u
0t
0q
0p
1n
0l
0i
0h
1g
1f
0e
0d
0c
1`
1_
#190
0$
0T
#195
1$
1T
b10000 (
b11100010111101111000010011000101 )
b10001 K
1!!
0~
0r
1p
1i
1h
0g
0_
0^
0]
0\
1[
#200
0$
0T
#205
1$
1T
b10001 (
b11010101000100111101001010101010 )
b10010 K
0!!
1~
0}
1|
1z
0y
1v
0u
1s
1q
0m
0j
0i
0h
1g
0f
1e
1c
0b
1_
#210
0$
0T
#215
1$
1T
b10010 (
b1110010101011111111011111100101 )
b10011 K
1!!
0~
1}
0|
1y
1w
1u
1r
1m
1l
0k
1j
1h
0g
1f
0e
1b
0`
0_
1^
#220
0$
0T
#225
1$
1T
b10011 (
b10111011110100100111001001110111 )
b10100 K
1~
1{
0x
0w
0u
0p
0o
0m
0l
1k
0j
1i
1g
1d
0a
1`
1_
#230
0$
0T
#235
1$
1T
b10100 (
b10001001001100101101011000010010 )
b10101 K
0!!
0}
0z
0y
1u
0r
1p
1j
0i
0h
0f
0c
0b
0_
0^
1]
#240
0$
0T
#245
1$
1T
b10101 (
b1000111111011001101101110001111 )
b10110 K
1!!
1}
1|
0{
1x
1w
0u
1t
0n
1m
1l
0k
1i
1h
1f
1e
0d
1a
0`
1_
#250
0$
0T
#255
1$
1T
b10110 (
b1111001001100000110100111110010 )
b10111 K
0!!
0}
0|
1{
1z
1y
0v
0s
1r
0p
0m
0l
1k
0i
0h
0f
0e
1d
1c
1b
0_
1^
#260
0$
0T
#265
1$
1T
b10111 (
b11100111011101101001011011001110 )
b11000 K
1}
1|
0{
0z
0w
1v
1u
0t
1s
0r
0q
1p
1n
1m
1i
1f
1e
0d
0c
1`
1_
#270
0$
0T
#275
1$
1T
b11000 (
b11110100000000000111101011101000 )
b11001 K
0~
0}
1z
0u
1t
1r
1q
0p
0n
0m
0k
0j
0i
0g
0f
1c
0_
0^
0]
1\
#280
0$
0T
#285
1$
1T
b11001 (
b11100010110010100100111011000101 )
b11010 K
1!!
1}
0|
0z
1u
0s
0r
1n
1l
1i
1h
1f
0e
0c
1_
#290
0$
0T
#295
1$
1T
b11010 (
b101110010110000100100101011100 )
b11011 K
0!!
1|
1{
0x
1w
0v
0u
0n
1k
0h
1e
1d
0a
0`
0_
1^
#300
0$
0T
#305
1$
1T
b11011 (
b11011110100011100010100010111101 )
b11100 K
1!!
1z
0y
1x
0w
1r
0q
1n
1m
0k
0i
1h
1c
0b
1a
1`
1_
#310
0$
0T
#315
1$
1T
b11100 (
b10010110101010110101100000101101 )
b11101 K
0{
0x
1s
0r
1q
1o
0m
1j
0d
0a
0_
0^
1]
#320
0$
0T
#325
1$
1T
b11101 (
b10110010101001110010011001100101 )
b11110 K
0|
1y
1v
1u
0t
0s
1r
0q
1m
0l
0e
1b
1_
#330
0$
0T
#335
1$
1T
b11110 (
b10110001111011110110001001100011 )
b11111 K
1~
0}
0u
1q
1l
1i
1g
0f
0_
1^
#340
0$
0T
#345
1$
1T
b11111 (
b101011100111000011100001010 )
b100000 K
0!!
1|
0z
0y
1w
1u
0r
0q
1p
0m
0l
1k
0h
1e
0c
0b
0`
1_
#350
0$
0T
#355
1$
1T
b100000 (
b11000000001110110010001010000000 )
b100001 K
0~
0|
1x
0w
0u
1r
0p
1l
0i
0g
0e
1a
1`
0_
0^
0]
0\
0[
1Z
#360
0$
0T
#365
1$
1T
b100001 (
b10000011001000010000100100000 )
b100010 K
1z
0x
1w
0v
0o
0n
1m
0l
0k
1i
1c
0a
0`
1_
#370
0$
0T
#375
1$
1T
b100010 (
b1010101011110000100010110101010 )
b100011 K
1~
1|
1x
1u
0r
1q
0m
1l
1k
1g
1e
1a
0_
1^
#380
0$
0T
#385
1$
1T
b100011 (
b11001110110011001100110010011101 )
b100100 K
1!!
0~
1}
1{
0z
0w
1t
1p
1m
0k
0j
1h
0g
1f
1d
0c
1`
1_
#390
0$
0T
#395
1$
1T
b100100 (
b11001011001000000011111010010110 )
b100101 K
0!!
1~
0|
1v
1s
1r
0q
0p
0m
0l
1j
0i
0h
1g
0e
0_
0^
1]
#400
0$
0T
#405
1$
1T
b100101 (
b10001001100000111011100000010011 )
b100110 K
1!!
0}
0x
0v
0u
1p
1o
1n
0j
1h
0f
0a
1_
#410
0$
0T
#415
1$
1T
b100110 (
b10000110101111000011100000001101 )
b100111 K
0~
1}
1|
0{
0p
0o
0n
1m
1l
1k
1j
0g
1f
1e
0d
0_
1^
#420
0$
0T
#425
1$
1T
b100111 (
b10101001101001111101011001010011 )
b101000 K
1~
0}
0|
1{
1y
1v
1u
0t
0r
1q
1p
1o
1n
0l
0k
1g
0f
0e
1d
1b
1_
#430
0$
0T
#435
1$
1T
b101000 (
b110101100111111101110101101011 )
b101001 K
1|
0{
1z
1w
0v
1t
1l
1k
0j
1e
0d
1c
0`
0_
0^
0]
1\
#440
0$
0T
#445
1$
1T
b101001 (
b11101010101001100010101011010101 )
b101010 K
0~
1}
0|
1{
0z
1x
0w
1v
0u
0s
1r
0q
0p
0o
0l
0k
1j
0g
1f
0e
1d
0c
1a
1`
1_
#450
0$
0T
#455
1$
1T
b101010 (
b10000001000101110100101000000010 )
b101011 K
0!!
1~
0}
0{
0y
0x
0r
1q
1o
1k
0j
0h
1g
0f
0d
0b
0a
0_
1^
#460
0$
0T
#465
1$
1T
b101011 (
b11010111010101100011111010101110 )
b101100 K
1}
1|
1z
1x
1u
1s
1r
0q
0o
1i
1f
1e
1c
1a
1_
#470
0$
0T
#475
1$
1T
b101100 (
b1110111111111110100100011101 )
b101101 K
1!!
0~
1{
0z
0x
1w
0v
0u
0s
1q
1p
1o
1l
1j
1h
0g
1d
0c
0a
0`
0_
0^
1]
#480
0$
0T
#485
1$
1T
b101101 (
b11100111110001010111001011001111 )
b101110 K
1~
0{
1y
1x
0w
1v
0t
1s
0p
0n
0l
0k
0j
1g
0d
1b
1a
1`
1_
#490
0$
0T
#495
1$
1T
b101110 (
b10001100001000100100100100011 )
b101111 K
0}
0|
1z
0y
0x
1w
0v
1t
0s
0r
0o
0i
0f
0e
1c
0b
0a
0`
0_
1^
#500
0$
0T
#505
1$
1T
b101111 (
b101000010010110010100001010 )
b110000 K
0!!
1|
0z
1u
0t
1r
1o
0m
1l
0h
1e
0c
1_
#510
0$
0T
#515
1$
1T
b110000 (
b11100101011100110000101011001010 )
b110001 K
1y
1x
0w
1v
0u
1t
0r
0q
1n
0l
1k
1j
1i
1b
1a
1`
0_
0^
0]
0\
1[
#520
0$
0T
#525
1$
1T
b110001 (
b10011110001100010100110000111100 )
b110010 K
0~
1}
1{
1z
0y
0x
0v
1u
1q
0n
0i
0g
1f
1d
1c
0b
0a
1_
#530
0$
0T
#535
1$
1T
b110010 (
b1111001011010001011110111110010 )
b110011 K
1~
0}
0|
1y
1x
1w
1s
1r
0q
1p
0o
1l
0k
1i
1g
0f
0e
1b
1a
0`
0_
1^
#540
0$
0T
#545
1$
1T
b110011 (
b1000101001011100110000110001010 )
b110100 K
1|
0{
0z
0y
0u
0t
0s
1q
0p
1n
1m
0i
1e
0d
0c
0b
1_
#550
0$
0T
#555
1$
1T
b110100 (
b100000110001001011001101000001 )
b110101 K
1!!
0~
0|
1y
0x
1v
1s
0q
1p
0n
0l
0j
1i
1h
0g
0e
1b
0a
0_
0^
1]
#560
0$
0T
#565
1$
1T
b110101 (
b11101100010010110011010011011000 )
b110110 K
0!!
1|
1{
1x
0w
0v
1u
0p
1o
1n
0m
1l
0h
1e
1d
1a
1`
1_
#570
0$
0T
#575
1$
1T
b110110 (
b111100001000001111001101111000 )
b110111 K
1z
0x
1w
1v
0u
1q
1p
0o
0n
0l
1j
0i
1c
0a
0`
0_
1^
#580
0$
0T
#585
1$
1T
b110111 (
b11000100100010100001001010001001 )
b111000 K
1!!
0{
0z
0y
1x
0w
0r
0q
0p
1n
1l
0j
1h
0d
0c
0b
1a
1`
1_
#590
0$
0T
#595
1$
1T
b111000 (
b1110101110001010000110111101011 )
b111001 K
1~
1z
1y
1w
0v
1u
1t
0s
1o
0n
1m
0l
1i
1g
1c
1b
0`
0_
0^
0]
1\
#600
0$
0T
#605
1$
1T
b111001 (
b1011011000000100110010110110110 )
b111010 K
0!!
1}
0|
1{
0y
0t
1r
1q
0o
1n
0m
0i
0h
1f
0e
1d
0b
1_
#610
0$
0T
#615
1$
1T
b111010 (
b1100011010010111111100111000110 )
b111011 K
0{
0z
1y
0u
1t
1s
1p
1o
1l
1i
0d
0c
1b
0_
1^
#620
0$
0T
