sequential/0110_1010/seqdet.v
module seqdet(serial_in, reset, clk, serial_out);
    input serial_in, clk, reset;
    output reg serial_out;

parameter s0 =0, s1 =1, s2 =2,s3 =3,s4 =4,s5 =5,s6 =6;
reg [2:0] PS, NS;

always @(posedge clk or posedge reset) begin
  if (reset) begin
    PS<=s0;
  end
  else PS<=NS;

end

always @(*) begin
  case (PS)
        s0: begin
            NS=serial_in?s2:s1;
            serial_out=0;          
        end
        s1: begin
            NS=serial_in?s3:s1;
            serial_out=0;          
        end
        s2: begin
            NS=serial_in?s2:s4;
            serial_out=0;          
        end
        s3: begin
            NS=serial_in?s5:s4;
            serial_out=0;          
        end
        s4: begin
            NS=serial_in?s6:s1;
            serial_out=0;          
        end
        s5: begin
            NS=serial_in?s2:s4;
            serial_out=serial_in?0:1;          
        end
        s6: begin
            NS=serial_in?s5:s4;
            serial_out=serial_in?0:1;          
        end
        
        default: begin
          NS=s0;
          serial_out=0;
        end

  endcase

end
endmodule

sequential/0110_1010/seqdet_tb.v
`timescale 1ns / 1ns
`include "seqdet.v"

module seqdet_tb;
reg clk, x, rst;
wire z;

seqdet s1(x,rst, clk, z);

initial begin
    $dumpfile("sequence.vcd");
    $dumpvars(0, seqdet_tb);
    rst=1'b1; clk=1'b0;
    #15 rst=1'b0;


end

always #5 clk=~clk;

initial begin
    #12 x=0; #10 x=1; #10 x=1; #10 x=0; #10 x=1; #10 x=0; #10 x=1; #10 x=1; #10 x=0; #10 x=1; #10 x=0; #10 x=1; #10 x=0;
    #10 $finish;
end

endmodule

sequential/0110_1010/sequence.vcd
$date
	Wed Aug 25 15:00:43 2021
$end
$version
	Icarus Verilog
$end
$timescale
	1ns
$end
$scope module seqdet_tb $end
$var wire 1 ! z $end
$var reg 1 " clk $end
$var reg 1 # rst $end
$var reg 1 $ x $end
$scope module s1 $end
$var wire 1 " clk $end
$var wire 1 # reset $end
$var wire 1 $ serial_in $end
$var reg 3 % NS [2:0] $end
$var reg 3 & PS [2:0] $end
$var reg 1 ! serial_out $end
$upscope $end
$upscope $end
$enddefinitions $end
#0
$dumpvars
b0 &
b0xx %
x$
1#
0"
0!
$end
#5
1"
#10
0"
#12
b1 %
0$
#15
b1 &
1"
0#
#20
0"
#22
b11 %
1$
#25
b101 %
b11 &
1"
#30
0"
#35
b10 %
b101 &
1"
#40
0"
#42
1!
b100 %
0$
#45
0!
b1 %
b100 &
1"
#50
0"
#52
b110 %
1$
#55
b101 %
b110 &
1"
#60
0"
#62
1!
b100 %
0$
#65
0!
b1 %
b100 &
1"
#70
0"
#72
b110 %
1$
#75
b101 %
b110 &
1"
#80
0"
#85
b10 %
b101 &
1"
#90
0"
#92
1!
b100 %
0$
#95
0!
b1 %
b100 &
1"
#100
0"
#102
b110 %
1$
#105
b101 %
b110 &
1"
#110
0"
#112
1!
b100 %
0$
#115
0!
b1 %
b100 &
1"
#120
0"
#122
b110 %
1$
#125
b101 %
b110 &
1"
#130
0"
#132
1!
b100 %
0$
#135
0!
b1 %
b100 &
1"
