Sequential/seqdet_0110/seqdet.v
module seqdet(serial_in, out, clk, reset);
    input serial_in, clk, reset;
    output reg out;
    parameter  s0=0, s1=1, s2=2, s3=3;
    reg[1:0] PS, NS;

    always @(posedge clk or posedge reset)
        begin
            if (reset) 
                PS<=s0;
            else
                PS<=NS;
        end

    always @(PS, serial_in)
        begin
          case (PS)
            
            s0: begin
                    NS=serial_in?s0:s1;
                    out=serial_in?0:0;              
                end 
            s1: begin
                    NS=serial_in?s2:s1;
                    out=serial_in?0:0;              
                end 
            s2: begin
                    NS=serial_in?s3:s1;
                    out=serial_in?0:0;              
                end 
            s3: begin
                    NS=serial_in?s0:s1;
                    out=serial_in?0:1;              
                end
                 
            endcase
        end
 
endmodule

sequential/0110/seqdet_tb.v
`timescale 1ns / 1ns
`include "seqdet.v"

module seqdet_tb;
reg clk, x, rst;
wire z;

seqdet s1(x,z,clk,rst);

initial begin
    $dumpfile("sequence.vcd");
    $dumpvars(0, seqdet_tb);
    rst=1'b1; clk=1'b0;
    #15 rst=1'b0;


end

always #5 clk=~clk;

initial begin
    #12 x=0; #10 x=1; #10 x=0; #10 x=1; #10 x=1; #10 x=0;
    #10 $finish;
end

endmodule

sequential/0110/sequence.vcd
$date
	Wed Jun 02 16:41:29 2021
$end
$version
	Icarus Verilog
$end
$timescale
	1ns
$end
$scope module seqdet_tb $end
$var wire 1 ! z $end
$var reg 1 " clk $end
$var reg 1 # rst $end
$var reg 1 $ x $end
$scope module s1 $end
$var wire 1 " clk $end
$var wire 1 # reset $end
$var wire 1 $ serial_in $end
$var reg 2 % NS [1:0] $end
$var reg 2 & PS [1:0] $end
$var reg 1 ! out $end
$upscope $end
$upscope $end
$enddefinitions $end
#0
$dumpvars
b0 &
b0x %
x$
1#
0"
0!
$end
#5
1"
#10
0"
#12
b1 %
0$
#15
b1 &
1"
0#
#20
0"
#22
b10 %
1$
#25
b11 %
b10 &
1"
#30
0"
#32
b1 %
0$
#35
b1 &
1"
#40
0"
#42
b10 %
1$
#45
b11 %
b10 &
1"
#50
0"
#55
b0 %
b11 &
1"
#60
0"
#62
1!
b1 %
0$
#65
0!
b1 &
1"
